iflow_mcp_tidal_mcp-0.1.2.dist-info/licenses/LICENSE
mcp_server/__init__.py
mcp_server/server.py
mcp_server/utils.py
tidal_api/__init__.py
tidal_api/app.py
tidal_api/browser_session.py
tidal_api/utils.py
iflow_mcp_tidal_mcp-0.1.2.dist-info/METADATA
iflow_mcp_tidal_mcp-0.1.2.dist-info/WHEEL
iflow_mcp_tidal_mcp-0.1.2.dist-info/entry_points.txt
iflow_mcp_tidal_mcp-0.1.2.dist-info/top_level.txt
iflow_mcp_tidal_mcp-0.1.2.dist-info/RECORD
