Metadata-Version: 2.4
Name: iflow-mcp_tidal-mcp
Version: 0.1.2
Requires-Python: >=3.10
License-File: LICENSE
Requires-Dist: flask>=3.1.0
Requires-Dist: mcp[cli]>=1.6.0
Requires-Dist: requests>=2.32.3
Requires-Dist: tidalapi>=0.8.3
Dynamic: license-file
